{
  "id": "cell_block",
  "name": "Cell Block B",
  "width": 48,
  "height": 24,
  "background": "#1a1420",
  "tiles": [
    "################################################",
    "#.......................#......................#",
    "#.......................#......................#",
    "#.......................#......................#",
    "#.......................#......................#",
    "#.......................#......................#",
    "#.......................#......................#",
    "#.......................#......................#",
    "#.......................#......................#",
    "#.......................#......................#",
    "#.......................#......................#",
    "#.......................#......................#",
    "#.......................#......................#",
    "#.......................#......................#",
    "#.......................#......................#",
    "#.......................#......................#",
    "#.....######............#......................#",
    "#.......................#......................#",
    "#.......................#......................#",
    "#..............................................#",
    "#..............................................#",
    "##################IIMMMMMMMMM###################",
    "#################...############################",
    "################################################"
  ],
  "entities": [
    {
      "type": "spawn",
      "x": 2,
      "y": 20
    },
    {
      "type": "pickup",
      "item": "scrap_metal",
      "x": 4,
      "y": 20
    },
    {
      "type": "npc",
      "x": 8,
      "y": 20,
      "name": "Marla (#12)",
      "color": "#7fd8e8",
      "wants": {
        "item": "glow_mushroom",
        "count": 1
      },
      "rewardItems": [
        {
          "item": "cloth",
          "count": 2
        }
      ],
      "rewardRecipes": [
        "recipe_smoke_bomb"
      ],
      "dialogAsk": "Psst. #67! Marla. #12. There's a GLOW MUSHROOM sealed under the ice over there — I've been staring at it for a month. Get it out, bring it here, I'll make it worth your while.",
      "dialogDone": "Beautiful. Here — cloth I've been hoarding, and a recipe: mushroom spores in a sock. Shake it and everything nearby takes a nap. Poof.",
      "dialogAfter": "Go. GO. Wave at the parking lot for me."
    },
    {
      "type": "pickup",
      "item": "scrap_metal",
      "x": 10,
      "y": 20
    },
    {
      "type": "pickup",
      "item": "cog",
      "x": 12,
      "y": 20
    },
    {
      "type": "pickup",
      "item": "plank",
      "x": 15,
      "y": 20
    },
    {
      "type": "hint",
      "x": 14,
      "y": 17,
      "text": "ice melts. ice shatters. treasure underneath"
    },
    {
      "type": "pickup",
      "item": "glow_mushroom",
      "x": 17,
      "y": 22
    },
    {
      "type": "note",
      "x": 18,
      "y": 22,
      "recipe": "recipe_spark_rod",
      "text": "Every gate runs to a fuse box. A cog on scrap makes a rod that BITES. Zap the box — or any metal touching it. Don't be standing on that metal. — Subject #19"
    },
    {
      "type": "hint",
      "x": 21,
      "y": 17,
      "text": "charge follows metal"
    },
    {
      "type": "door",
      "x": 24,
      "y": 20,
      "gate": true,
      "fuseId": "A"
    },
    {
      "type": "fusebox",
      "x": 27,
      "y": 19,
      "fuseId": "A"
    },
    {
      "type": "checkpoint",
      "x": 30,
      "y": 20
    },
    {
      "type": "pickup",
      "item": "cog",
      "x": 33,
      "y": 20
    },
    {
      "type": "enemy",
      "enemy": "crawler",
      "x": 36,
      "y": 20,
      "patrolMinX": 34,
      "patrolMaxX": 42
    },
    {
      "type": "pickup",
      "item": "scrap_metal",
      "x": 43,
      "y": 20
    },
    {
      "type": "door",
      "x": 45,
      "y": 20,
      "to": "next"
    }
  ]
}
